CHANGELOG.txt
LICENSE.txt
MANIFEST.in
README.txt
main.py
setup.py
Piweb.egg-info/PKG-INFO
Piweb.egg-info/SOURCES.txt
Piweb.egg-info/dependency_links.txt
Piweb.egg-info/top_level.txt
venv/Lib/site-packages/easy_install.py
venv/Lib/site-packages/playsound.py
venv/Lib/site-packages/pythoncom.py
venv/Lib/site-packages/pywin32.version.txt
venv/Lib/site-packages/_distutils_hack/__init__.py
venv/Lib/site-packages/_distutils_hack/override.py
venv/Lib/site-packages/adodbapi/__init__.py
venv/Lib/site-packages/adodbapi/ado_consts.py
venv/Lib/site-packages/adodbapi/adodbapi.py
venv/Lib/site-packages/adodbapi/apibase.py
venv/Lib/site-packages/adodbapi/is64bit.py
venv/Lib/site-packages/adodbapi/license.txt
venv/Lib/site-packages/adodbapi/process_connect_string.py
venv/Lib/site-packages/adodbapi/readme.txt
venv/Lib/site-packages/adodbapi/remote.py
venv/Lib/site-packages/adodbapi/schema_table.py
venv/Lib/site-packages/adodbapi/setup.py
venv/Lib/site-packages/adodbapi/examples/db_print.py
venv/Lib/site-packages/adodbapi/examples/db_table_names.py
venv/Lib/site-packages/adodbapi/examples/xls_read.py
venv/Lib/site-packages/adodbapi/examples/xls_write.py
venv/Lib/site-packages/adodbapi/test/adodbapitest.py
venv/Lib/site-packages/adodbapi/test/adodbapitestconfig.py
venv/Lib/site-packages/adodbapi/test/dbapi20.py
venv/Lib/site-packages/adodbapi/test/is64bit.py
venv/Lib/site-packages/adodbapi/test/setuptestframework.py
venv/Lib/site-packages/adodbapi/test/test_adodbapi_dbapi20.py
venv/Lib/site-packages/adodbapi/test/tryconnection.py
venv/Lib/site-packages/beautifulsoup4-4.9.3.dist-info/COPYING.txt
venv/Lib/site-packages/beautifulsoup4-4.9.3.dist-info/top_level.txt
venv/Lib/site-packages/bs4/__init__.py
venv/Lib/site-packages/bs4/dammit.py
venv/Lib/site-packages/bs4/diagnose.py
venv/Lib/site-packages/bs4/element.py
venv/Lib/site-packages/bs4/formatter.py
venv/Lib/site-packages/bs4/testing.py
venv/Lib/site-packages/bs4/builder/__init__.py
venv/Lib/site-packages/bs4/builder/_html5lib.py
venv/Lib/site-packages/bs4/builder/_htmlparser.py
venv/Lib/site-packages/bs4/builder/_lxml.py
venv/Lib/site-packages/bs4/tests/__init__.py
venv/Lib/site-packages/bs4/tests/test_builder_registry.py
venv/Lib/site-packages/bs4/tests/test_docs.py
venv/Lib/site-packages/certifi-2020.11.8.dist-info/top_level.txt
venv/Lib/site-packages/chardet-3.0.4.dist-info/entry_points.txt
venv/Lib/site-packages/chardet-3.0.4.dist-info/top_level.txt
venv/Lib/site-packages/comtypes-1.1.7-py3.9.egg-info/SOURCES.txt
venv/Lib/site-packages/comtypes-1.1.7-py3.9.egg-info/dependency_links.txt
venv/Lib/site-packages/comtypes-1.1.7-py3.9.egg-info/installed-files.txt
venv/Lib/site-packages/comtypes-1.1.7-py3.9.egg-info/top_level.txt
venv/Lib/site-packages/idna-2.10.dist-info/top_level.txt
venv/Lib/site-packages/pip-20.2.4.dist-info/LICENSE.txt
venv/Lib/site-packages/pip-20.2.4.dist-info/entry_points.txt
venv/Lib/site-packages/pip-20.2.4.dist-info/top_level.txt
venv/Lib/site-packages/playsound-1.2.2.dist-info/top_level.txt
venv/Lib/site-packages/pypiwin32-223.dist-info/top_level.txt
venv/Lib/site-packages/pyttsx3-2.90.dist-info/top_level.txt
venv/Lib/site-packages/pywin32-300.dist-info/top_level.txt
venv/Lib/site-packages/requests-2.25.0.dist-info/top_level.txt
venv/Lib/site-packages/setuptools-50.3.2.dist-info/dependency_links.txt
venv/Lib/site-packages/setuptools-50.3.2.dist-info/entry_points.txt
venv/Lib/site-packages/setuptools-50.3.2.dist-info/top_level.txt
venv/Lib/site-packages/slys-0.0.1.dist-info/LICENSE.txt
venv/Lib/site-packages/slys-0.0.1.dist-info/top_level.txt
venv/Lib/site-packages/soupsieve-2.0.1.dist-info/top_level.txt
venv/Lib/site-packages/urllib3-1.26.2.dist-info/LICENSE.txt
venv/Lib/site-packages/urllib3-1.26.2.dist-info/top_level.txt
venv/Lib/site-packages/wikipedia-1.4.0-py3.9.egg-info/SOURCES.txt
venv/Lib/site-packages/wikipedia-1.4.0-py3.9.egg-info/dependency_links.txt
venv/Lib/site-packages/wikipedia-1.4.0-py3.9.egg-info/installed-files.txt
venv/Lib/site-packages/wikipedia-1.4.0-py3.9.egg-info/requires.txt
venv/Lib/site-packages/wikipedia-1.4.0-py3.9.egg-info/top_level.txt
